hansel/__init__.py
hansel/_utils.py
hansel/crumb.py
hansel/mktree.py
hansel/pandas.py
hansel/utils.py
hansel/version.py
hansel/cli/__init__.py
hansel/cli/cli.py
hansel/cli/utils.py
hansel-1.0.2.dist-info/DESCRIPTION.rst
hansel-1.0.2.dist-info/METADATA
hansel-1.0.2.dist-info/RECORD
hansel-1.0.2.dist-info/WHEEL
hansel-1.0.2.dist-info/entry_points.txt
hansel-1.0.2.dist-info/metadata.json
hansel-1.0.2.dist-info/top_level.txt
