Metadata-Version: 2.0
Name: hansel
Version: 1.0.2
Summary: Easily traverse your structured folder tree.
Home-page: https://pypi.python.org/pypi/hansel
Author: alexsavio
Author-email: alexsavio@gmail.com
License: Apache 2.0
Platform: Linux/MacOSX
Classifier: Programming Language :: Python
Classifier: Development Status :: 4 - Beta
Classifier: Natural Language :: English
Classifier: Environment :: Console
Classifier: License :: OSI Approved :: Apache Software License
Classifier: Operating System :: OS Independent
Classifier: Topic :: Software Development :: Libraries :: Python Modules
Classifier: Operating System :: POSIX
Classifier: Operating System :: Unix
Classifier: Operating System :: MacOS
Classifier: Programming Language :: Python :: 3.5
Classifier: Programming Language :: Python :: 3.4
Classifier: Programming Language :: Python :: 2.7
Requires-Dist: six
Provides-Extra: testing
Requires-Dist: pandas; extra == 'testing'
Requires-Dist: pytest; extra == 'testing'
Requires-Dist: pytest-cov; extra == 'testing'
